[
    {
        "country": "China",
        "confirmed": 84494,
        "death": 4645,
        "recovered": 0
    },
    {
        "country": "S. Korea",
        "confirmed": 11065,
        "death": 263,
        "recovered": 0
    },
    {
        "country": "Japan",
        "confirmed": 16305,
        "death": 749,
        "recovered": 0
    },
    {
        "country": "Singapore",
        "confirmed": 28038,
        "death": 22,
        "recovered": 0
    },
    {
        "country": "Australia",
        "confirmed": 7045,
        "death": 98,
        "recovered": 0
    },
    {
        "country": "Malaysia",
        "confirmed": 6894,
        "death": 113,
        "recovered": 0
    },
    {
        "country": "Vietnam",
        "confirmed": 320,
        "death": 0,
        "recovered": 0
    },
    {
        "country": "Philippines",
        "confirmed": 12513,
        "death": 824,
        "recovered": 0
    },
    {
        "country": "Cambodia",
        "confirmed": 122,
        "death": 0,
        "recovered": 0
    },
    {
        "country": "New Zealand",
        "confirmed": 1149,
        "death": 21,
        "recovered": 0
    },
    {
        "country": "Italy",
        "confirmed": 225435,
        "death": 31908,
        "recovered": 0
    },
    {
        "country": "France",
        "confirmed": 140036,
        "death": 28059,
        "recovered": 0
    },
    {
        "country": "Germany",
        "confirmed": 174697,
        "death": 7935,
        "recovered": 0
    },
    {
        "country": "Spain",
        "confirmed": 231350,
        "death": 27650,
        "recovered": 0
    },
    {
        "country": "UK",
        "confirmed": 243699,
        "death": 34636,
        "recovered": 0
    },
    {
        "country": "Switzerland",
        "confirmed": 30504,
        "death": 1602,
        "recovered": 0
    },
    {
        "country": "Norway",
        "confirmed": 8197,
        "death": 232,
        "recovered": 0
    },
    {
        "country": "Sweden",
        "confirmed": 30143,
        "death": 3679,
        "recovered": 0
    },
    {
        "country": "Austria",
        "confirmed": 16154,
        "death": 629,
        "recovered": 0
    },
    {
        "country": "Croatia",
        "confirmed": 2226,
        "death": 95,
        "recovered": 0
    },
    {
        "country": "Israel",
        "confirmed": 16608,
        "death": 271,
        "recovered": 0
    },
    {
        "country": "Netherlands",
        "confirmed": 43995,
        "death": 5680,
        "recovered": 0
    },
    {
        "country": "Azerbaijan",
        "confirmed": 3274,
        "death": 39,
        "recovered": 0
    },
    {
        "country": "Denmark",
        "confirmed": 10927,
        "death": 547,
        "recovered": 0
    },
    {
        "country": "Georgia",
        "confirmed": 701,
        "death": 12,
        "recovered": 0
    },
    {
        "country": "Greece",
        "confirmed": 2834,
        "death": 163,
        "recovered": 0
    },
    {
        "country": "Romania",
        "confirmed": 16871,
        "death": 1097,
        "recovered": 0
    },
    {
        "country": "Finland",
        "confirmed": 6347,
        "death": 298,
        "recovered": 0
    },
    {
        "country": "Russia",
        "confirmed": 290678,
        "death": 2722,
        "recovered": 0
    },
    {
        "country": "Belarus",
        "confirmed": 29650,
        "death": 165,
        "recovered": 0
    },
    {
        "country": "Belgium",
        "confirmed": 55280,
        "death": 9052,
        "recovered": 0
    },
    {
        "country": "Estonia",
        "confirmed": 1774,
        "death": 63,
        "recovered": 0
    },
    {
        "country": "Ireland",
        "confirmed": 24112,
        "death": 1543,
        "recovered": 0
    },
    {
        "country": "Lithuania",
        "confirmed": 1541,
        "death": 56,
        "recovered": 0
    },
    {
        "country": "Monaco",
        "confirmed": 98,
        "death": 1,
        "recovered": 0
    },
    {
        "country": "North Macedonia",
        "confirmed": 1792,
        "death": 101,
        "recovered": 0
    },
    {
        "country": "San Marino",
        "confirmed": 668,
        "death": 41,
        "recovered": 0
    },
    {
        "country": "Thailand",
        "confirmed": 3031,
        "death": 56,
        "recovered": 0
    },
    {
        "country": "India",
        "confirmed": 96169,
        "death": 3029,
        "recovered": 0
    },
    {
        "country": "Nepal",
        "confirmed": 304,
        "death": 2,
        "recovered": 0
    },
    {
        "country": "Sri Lanka",
        "confirmed": 981,
        "death": 9,
        "recovered": 0
    },
    {
        "country": "Iran",
        "confirmed": 120198,
        "death": 6988,
        "recovered": 0
    },
    {
        "country": "Kuwait",
        "confirmed": 14850,
        "death": 112,
        "recovered": 0
    },
    {
        "country": "Bahrain",
        "confirmed": 6930,
        "death": 12,
        "recovered": 0
    },
    {
        "country": "UAE",
        "confirmed": 23358,
        "death": 220,
        "recovered": 0
    },
    {
        "country": "Iraq",
        "confirmed": 3404,
        "death": 123,
        "recovered": 0
    },
    {
        "country": "Oman",
        "confirmed": 5379,
        "death": 23,
        "recovered": 0
    },
    {
        "country": "Pakistan",
        "confirmed": 42125,
        "death": 903,
        "recovered": 0
    },
    {
        "country": "Lebanon",
        "confirmed": 911,
        "death": 26,
        "recovered": 0
    },
    {
        "country": "Afghanistan",
        "confirmed": 7072,
        "death": 173,
        "recovered": 0
    },
    {
        "country": "Egypt",
        "confirmed": 12229,
        "death": 630,
        "recovered": 0
    },
    {
        "country": "Qatar",
        "confirmed": 32604,
        "death": 15,
        "recovered": 0
    },
    {
        "country": "USA",
        "confirmed": 1432265,
        "death": 87180,
        "recovered": 0
    },
    {
        "country": "Canada",
        "confirmed": 76204,
        "death": 5702,
        "recovered": 0
    },
    {
        "country": "Brazil",
        "confirmed": 233142,
        "death": 15633,
        "recovered": 0
    },
    {
        "country": "Mexico",
        "confirmed": 47144,
        "death": 5045,
        "recovered": 0
    },
    {
        "country": "Ecuador",
        "confirmed": 32723,
        "death": 2688,
        "recovered": 0
    },
    {
        "country": "Algeria",
        "confirmed": 7019,
        "death": 548,
        "recovered": 0
    },
    {
        "country": "Nigeria",
        "confirmed": 5959,
        "death": 182,
        "recovered": 0
    },
    {
        "country": "Czechia",
        "confirmed": 8475,
        "death": 298,
        "recovered": 0
    },
    {
        "country": "Iceland",
        "confirmed": 1802,
        "death": 10,
        "recovered": 0
    },
    {
        "country": "Armenia",
        "confirmed": 4823,
        "death": 61,
        "recovered": 0
    },
    {
        "country": "Luxembourg",
        "confirmed": 3945,
        "death": 107,
        "recovered": 0
    },
    {
        "country": "Indonesia",
        "confirmed": 17514,
        "death": 1148,
        "recovered": 0
    },
    {
        "country": "Dominican Republic",
        "confirmed": 12314,
        "death": 428,
        "recovered": 0
    },
    {
        "country": "Portugal",
        "confirmed": 29036,
        "death": 1218,
        "recovered": 0
    },
    {
        "country": "Andorra",
        "confirmed": 761,
        "death": 51,
        "recovered": 0
    },
    {
        "country": "Latvia",
        "confirmed": 1008,
        "death": 19,
        "recovered": 0
    },
    {
        "country": "Jordan",
        "confirmed": 613,
        "death": 9,
        "recovered": 0
    },
    {
        "country": "Morocco",
        "confirmed": 6870,
        "death": 192,
        "recovered": 0
    },
    {
        "country": "Saudi Arabia",
        "confirmed": 54752,
        "death": 312,
        "recovered": 0
    },
    {
        "country": "Tunisia",
        "confirmed": 1037,
        "death": 45,
        "recovered": 0
    },
    {
        "country": "Senegal",
        "confirmed": 2480,
        "death": 25,
        "recovered": 0
    },
    {
        "country": "Poland",
        "confirmed": 18529,
        "death": 925,
        "recovered": 0
    },
    {
        "country": "Ukraine",
        "confirmed": 18616,
        "death": 535,
        "recovered": 0
    },
    {
        "country": "Argentina",
        "confirmed": 7805,
        "death": 366,
        "recovered": 0
    },
    {
        "country": "Chile",
        "confirmed": 43781,
        "death": 450,
        "recovered": 0
    },
    {
        "country": "Bosnia and Herzegovina",
        "confirmed": 2289,
        "death": 132,
        "recovered": 0
    },
    {
        "country": "Hungary",
        "confirmed": 3535,
        "death": 462,
        "recovered": 0
    },
    {
        "country": "Slovenia",
        "confirmed": 1466,
        "death": 104,
        "recovered": 0
    },
    {
        "country": "Liechtenstein",
        "confirmed": 83,
        "death": 1,
        "recovered": 0
    },
    {
        "country": "Gibraltar",
        "confirmed": 147,
        "death": 1,
        "recovered": 0
    },
    {
        "country": "occupied Palestinian territory",
        "confirmed": 560,
        "death": 4,
        "recovered": 0
    },
    {
        "country": "Saint Martin",
        "confirmed": 39,
        "death": 3,
        "recovered": 0
    },
    {
        "country": "St. Barth",
        "confirmed": 6,
        "death": 0,
        "recovered": 0
    },
    {
        "country": "Serbia",
        "confirmed": 10610,
        "death": 230,
        "recovered": 0
    },
    {
        "country": "Bhutan",
        "confirmed": 21,
        "death": 0,
        "recovered": 0
    },
    {
        "country": "Cameroon",
        "confirmed": 3047,
        "death": 139,
        "recovered": 0
    },
    {
        "country": "South Africa",
        "confirmed": 15515,
        "death": 264,
        "recovered": 0
    },
    {
        "country": "Holy See",
        "confirmed": 12,
        "death": 0,
        "recovered": 0
    },
    {
        "country": "Slovakia",
        "confirmed": 1494,
        "death": 28,
        "recovered": 0
    },
    {
        "country": "Colombia",
        "confirmed": 14939,
        "death": 562,
        "recovered": 0
    },
    {
        "country": "Peru",
        "confirmed": 88541,
        "death": 2523,
        "recovered": 0
    },
    {
        "country": "Togo",
        "confirmed": 301,
        "death": 11,
        "recovered": 0
    },
    {
        "country": "Malta",
        "confirmed": 553,
        "death": 6,
        "recovered": 0
    },
    {
        "country": "Bulgaria",
        "confirmed": 2235,
        "death": 110,
        "recovered": 0
    },
    {
        "country": "Moldova",
        "confirmed": 6060,
        "death": 211,
        "recovered": 0
    },
    {
        "country": "Faroe Islands",
        "confirmed": 187,
        "death": 0,
        "recovered": 0
    },
    {
        "country": "Maldives",
        "confirmed": 1094,
        "death": 4,
        "recovered": 0
    },
    {
        "country": "Costa Rica",
        "confirmed": 853,
        "death": 10,
        "recovered": 0
    },
    {
        "country": "French Guiana",
        "confirmed": 197,
        "death": 1,
        "recovered": 0
    },
    {
        "country": "Martinique",
        "confirmed": 192,
        "death": 14,
        "recovered": 0
    },
    {
        "country": "Albania",
        "confirmed": 948,
        "death": 31,
        "recovered": 0
    },
    {
        "country": "Bangladesh",
        "confirmed": 22268,
        "death": 328,
        "recovered": 0
    },
    {
        "country": "Paraguay",
        "confirmed": 786,
        "death": 11,
        "recovered": 0
    },
    {
        "country": "Brunei",
        "confirmed": 141,
        "death": 1,
        "recovered": 0
    },
    {
        "country": "Mongolia",
        "confirmed": 136,
        "death": 0,
        "recovered": 0
    },
    {
        "country": "Cyprus",
        "confirmed": 916,
        "death": 23,
        "recovered": 0
    },
    {
        "country": "Guernsey",
        "confirmed": 252,
        "death": 13,
        "recovered": 0
    },
    {
        "country": "Panama",
        "confirmed": 9449,
        "death": 269,
        "recovered": 0
    },
    {
        "country": "Bolivia",
        "confirmed": 3826,
        "death": 165,
        "recovered": 0
    },
    {
        "country": "Jamaica",
        "confirmed": 517,
        "death": 9,
        "recovered": 0
    },
    {
        "country": "Burkina Faso",
        "confirmed": 796,
        "death": 51,
        "recovered": 0
    },
    {
        "country": "DRC",
        "confirmed": 1454,
        "death": 60,
        "recovered": 0
    },
    {
        "country": "French Polynesia",
        "confirmed": 60,
        "death": 0,
        "recovered": 0
    },
    {
        "country": "Turkey",
        "confirmed": 149435,
        "death": 4140,
        "recovered": 0
    },
    {
        "country": "Honduras",
        "confirmed": 2565,
        "death": 138,
        "recovered": 0
    },
    {
        "country": "Ivory Coast",
        "confirmed": 2109,
        "death": 27,
        "recovered": 0
    },
    {
        "country": "Jersey",
        "confirmed": 297,
        "death": 27,
        "recovered": 0
    },
    {
        "country": "Cuba",
        "confirmed": 1872,
        "death": 79,
        "recovered": 0
    },
    {
        "country": "Guyana",
        "confirmed": 117,
        "death": 10,
        "recovered": 0
    },
    {
        "country": "St. Vincent Grenadines",
        "confirmed": 17,
        "death": 0,
        "recovered": 0
    },
    {
        "country": "Sudan",
        "confirmed": 2591,
        "death": 105,
        "recovered": 0
    },
    {
        "country": "Puerto Rico",
        "confirmed": 2646,
        "death": 123,
        "recovered": 0
    },
    {
        "country": "Venezuela",
        "confirmed": 541,
        "death": 10,
        "recovered": 0
    },
    {
        "country": "Antigua and Barbuda",
        "confirmed": 25,
        "death": 3,
        "recovered": 0
    },
    {
        "country": "Guadeloupe",
        "confirmed": 155,
        "death": 13,
        "recovered": 0
    },
    {
        "country": "Trinidad and Tobago",
        "confirmed": 116,
        "death": 8,
        "recovered": 0
    },
    {
        "country": "Cayman Islands",
        "confirmed": 94,
        "death": 1,
        "recovered": 0
    },
    {
        "country": "Ethiopia",
        "confirmed": 317,
        "death": 5,
        "recovered": 0
    },
    {
        "country": "Gabon",
        "confirmed": 1320,
        "death": 11,
        "recovered": 0
    },
    {
        "country": "Ghana",
        "confirmed": 5735,
        "death": 29,
        "recovered": 0
    },
    {
        "country": "Guinea",
        "confirmed": 2727,
        "death": 16,
        "recovered": 0
    },
    {
        "country": "Kenya",
        "confirmed": 887,
        "death": 50,
        "recovered": 0
    },
    {
        "country": "Reunion",
        "confirmed": 443,
        "death": 0,
        "recovered": 0
    },
    {
        "country": "Kazakhstan",
        "confirmed": 6440,
        "death": 34,
        "recovered": 0
    },
    {
        "country": "Curacao",
        "confirmed": 16,
        "death": 1,
        "recovered": 0
    },
    {
        "country": "Namibia",
        "confirmed": 16,
        "death": 0,
        "recovered": 0
    },
    {
        "country": "CAR",
        "confirmed": 327,
        "death": 0,
        "recovered": 0
    },
    {
        "country": "Congo",
        "confirmed": 410,
        "death": 15,
        "recovered": 0
    },
    {
        "country": "Equatorial Guinea",
        "confirmed": 719,
        "death": 7,
        "recovered": 0
    },
    {
        "country": "Eswatini",
        "confirmed": 203,
        "death": 2,
        "recovered": 0
    },
    {
        "country": "Mauritania",
        "confirmed": 62,
        "death": 4,
        "recovered": 0
    },
    {
        "country": "Mayotte",
        "confirmed": 1342,
        "death": 18,
        "recovered": 0
    },
    {
        "country": "Uzbekistan",
        "confirmed": 2762,
        "death": 12,
        "recovered": 0
    },
    {
        "country": "Uruguay",
        "confirmed": 734,
        "death": 19,
        "recovered": 0
    },
    {
        "country": "Guatemala",
        "confirmed": 1763,
        "death": 33,
        "recovered": 0
    },
    {
        "country": "Saint Lucia",
        "confirmed": 18,
        "death": 0,
        "recovered": 0
    },
    {
        "country": "Suriname",
        "confirmed": 10,
        "death": 1,
        "recovered": 0
    },
    {
        "country": "Rwanda",
        "confirmed": 292,
        "death": 0,
        "recovered": 0
    },
    {
        "country": "Seychelles",
        "confirmed": 11,
        "death": 0,
        "recovered": 0
    },
    {
        "country": "Guam",
        "confirmed": 149,
        "death": 5,
        "recovered": 0
    },
    {
        "country": "Somalia",
        "confirmed": 1421,
        "death": 56,
        "recovered": 0
    },
    {
        "country": "Bahamas",
        "confirmed": 96,
        "death": 11,
        "recovered": 0
    },
    {
        "country": "Grenadines",
        "confirmed": 17,
        "death": 0,
        "recovered": 0
    },
    {
        "country": "Aruba",
        "confirmed": 101,
        "death": 3,
        "recovered": 0
    },
    {
        "country": "U.S. Virgin Islands",
        "confirmed": 69,
        "death": 6,
        "recovered": 0
    },
    {
        "country": "Benin",
        "confirmed": 339,
        "death": 2,
        "recovered": 0
    },
    {
        "country": "Liberia",
        "confirmed": 226,
        "death": 21,
        "recovered": 0
    },
    {
        "country": "Tanzania",
        "confirmed": 509,
        "death": 21,
        "recovered": 0
    },
    {
        "country": "Montenegro",
        "confirmed": 325,
        "death": 9,
        "recovered": 0
    },
    {
        "country": "Kyrgyzstan",
        "confirmed": 1216,
        "death": 14,
        "recovered": 0
    },
    {
        "country": "Greenland",
        "confirmed": 11,
        "death": 0,
        "recovered": 0
    },
    {
        "country": "Djibouti",
        "confirmed": 1401,
        "death": 4,
        "recovered": 0
    },
    {
        "country": "Barbados",
        "confirmed": 86,
        "death": 7,
        "recovered": 0
    },
    {
        "country": "Montserrat",
        "confirmed": 11,
        "death": 1,
        "recovered": 0
    },
    {
        "country": "Mauritius",
        "confirmed": 334,
        "death": 10,
        "recovered": 0
    },
    {
        "country": "Zambia",
        "confirmed": 753,
        "death": 7,
        "recovered": 0
    },
    {
        "country": "Gambia",
        "confirmed": 24,
        "death": 1,
        "recovered": 0
    },
    {
        "country": "Fiji",
        "confirmed": 18,
        "death": 0,
        "recovered": 0
    },
    {
        "country": "New Caledonia",
        "confirmed": 18,
        "death": 0,
        "recovered": 0
    },
    {
        "country": "Herzegovina",
        "confirmed": 44,
        "death": 0,
        "recovered": 0
    },
    {
        "country": "Bermuda",
        "confirmed": 123,
        "death": 9,
        "recovered": 0
    },
    {
        "country": "El Salvador",
        "confirmed": 1338,
        "death": 27,
        "recovered": 0
    },
    {
        "country": "Nicaragua",
        "confirmed": 25,
        "death": 8,
        "recovered": 0
    },
    {
        "country": "Sint Maarten",
        "confirmed": 78,
        "death": 15,
        "recovered": 0
    },
    {
        "country": "Chad",
        "confirmed": 503,
        "death": 53,
        "recovered": 0
    },
    {
        "country": "Niger",
        "confirmed": 904,
        "death": 54,
        "recovered": 0
    },
    {
        "country": "Papua New Guinea",
        "confirmed": 8,
        "death": 0,
        "recovered": 0
    },
    {
        "country": "Isle of Man",
        "confirmed": 335,
        "death": 24,
        "recovered": 0
    },
    {
        "country": "Timor-Leste",
        "confirmed": 24,
        "death": 0,
        "recovered": 0
    },
    {
        "country": "Haiti",
        "confirmed": 358,
        "death": 20,
        "recovered": 0
    },
    {
        "country": "Cabo Verde",
        "confirmed": 328,
        "death": 3,
        "recovered": 0
    },
    {
        "country": "Zimbabwe",
        "confirmed": 44,
        "death": 4,
        "recovered": 0
    },
    {
        "country": "Madagascar",
        "confirmed": 304,
        "death": 1,
        "recovered": 0
    },
    {
        "country": "Angola",
        "confirmed": 48,
        "death": 2,
        "recovered": 0
    },
    {
        "country": "Eritrea",
        "confirmed": 39,
        "death": 0,
        "recovered": 0
    },
    {
        "country": "Uganda",
        "confirmed": 227,
        "death": 0,
        "recovered": 0
    },
    {
        "country": "Kosovo",
        "confirmed": 955,
        "death": 29,
        "recovered": 0
    },
    {
        "country": "Syria",
        "confirmed": 58,
        "death": 3,
        "recovered": 0
    },
    {
        "country": "Grenada",
        "confirmed": 22,
        "death": 0,
        "recovered": 0
    },
    {
        "country": "Mozambique",
        "confirmed": 137,
        "death": 0,
        "recovered": 0
    },
    {
        "country": "Myanmar",
        "confirmed": 187,
        "death": 6,
        "recovered": 0
    },
    {
        "country": "Belize",
        "confirmed": 18,
        "death": 2,
        "recovered": 0
    },
    {
        "country": "Dominica",
        "confirmed": 16,
        "death": 0,
        "recovered": 0
    },
    {
        "country": "Turks and Caicos",
        "confirmed": 12,
        "death": 1,
        "recovered": 0
    },
    {
        "country": "Laos",
        "confirmed": 19,
        "death": 0,
        "recovered": 0
    },
    {
        "country": "Libya",
        "confirmed": 65,
        "death": 3,
        "recovered": 0
    },
    {
        "country": "Saint Kitts and Nevis",
        "confirmed": 15,
        "death": 0,
        "recovered": 0
    },
    {
        "country": "Guinea-Bissau",
        "confirmed": 990,
        "death": 4,
        "recovered": 0
    },
    {
        "country": "Mali",
        "confirmed": 860,
        "death": 52,
        "recovered": 0
    },
    {
        "country": "Anguilla",
        "confirmed": 3,
        "death": 0,
        "recovered": 0
    },
    {
        "country": "British Virgin Islands",
        "confirmed": 8,
        "death": 1,
        "recovered": 0
    },
    {
        "country": "Northern Mariana Islands (Commonwealth of the)",
        "confirmed": 21,
        "death": 2,
        "recovered": 0
    },
    {
        "country": "Botswana",
        "confirmed": 25,
        "death": 1,
        "recovered": 0
    },
    {
        "country": "Burundi",
        "confirmed": 42,
        "death": 1,
        "recovered": 0
    },
    {
        "country": "Sierra Leone",
        "confirmed": 505,
        "death": 32,
        "recovered": 0
    },
    {
        "country": "Malawi",
        "confirmed": 70,
        "death": 3,
        "recovered": 0
    },
    {
        "country": "Bonaire, Sint Eustatius and Saba",
        "confirmed": 6,
        "death": 0,
        "recovered": 0
    },
    {
        "country": "Falkland Islands",
        "confirmed": 13,
        "death": 0,
        "recovered": 0
    },
    {
        "country": "South Sudan",
        "confirmed": 282,
        "death": 4,
        "recovered": 0
    },
    {
        "country": "Sao Tome and Principe",
        "confirmed": 208,
        "death": 7,
        "recovered": 0
    },
    {
        "country": "Saint Pierre Miquelon",
        "confirmed": 1,
        "death": 0,
        "recovered": 0
    },
    {
        "country": "Yemen",
        "confirmed": 132,
        "death": 21,
        "recovered": 0
    },
    {
        "country": "Comoros",
        "confirmed": 11,
        "death": 1,
        "recovered": 0
    },
    {
        "country": "Tajikistan",
        "confirmed": 1322,
        "death": 41,
        "recovered": 0
    },
    {
        "country": "Lesotho",
        "confirmed": 1,
        "death": 0,
        "recovered": 0
    }
]