[
    {
        "country": "China",
        "confirmed": 84404,
        "death": 4643,
        "recovered": 0
    },
    {
        "country": "S. Korea",
        "confirmed": 10804,
        "death": 254,
        "recovered": 0
    },
    {
        "country": "Japan",
        "confirmed": 15231,
        "death": 521,
        "recovered": 0
    },
    {
        "country": "Singapore",
        "confirmed": 18778,
        "death": 876,
        "recovered": 0
    },
    {
        "country": "Australia",
        "confirmed": 6941,
        "death": 97,
        "recovered": 0
    },
    {
        "country": "Malaysia",
        "confirmed": 6656,
        "death": 108,
        "recovered": 0
    },
    {
        "country": "Vietnam",
        "confirmed": 318,
        "death": 0,
        "recovered": 0
    },
    {
        "country": "Philippines",
        "confirmed": 9684,
        "death": 637,
        "recovered": 0
    },
    {
        "country": "Cambodia",
        "confirmed": 122,
        "death": 0,
        "recovered": 0
    },
    {
        "country": "New Zealand",
        "confirmed": 1147,
        "death": 21,
        "recovered": 0
    },
    {
        "country": "Italy",
        "confirmed": 211938,
        "death": 29079,
        "recovered": 0
    },
    {
        "country": "France",
        "confirmed": 130242,
        "death": 25165,
        "recovered": 0
    },
    {
        "country": "Germany",
        "confirmed": 163860,
        "death": 6831,
        "recovered": 0
    },
    {
        "country": "Spain",
        "confirmed": 219764,
        "death": 25428,
        "recovered": 0
    },
    {
        "country": "UK",
        "confirmed": 190588,
        "death": 28734,
        "recovered": 0
    },
    {
        "country": "Switzerland",
        "confirmed": 29898,
        "death": 1476,
        "recovered": 0
    },
    {
        "country": "Norway",
        "confirmed": 8099,
        "death": 217,
        "recovered": 0
    },
    {
        "country": "Sweden",
        "confirmed": 22721,
        "death": 2769,
        "recovered": 0
    },
    {
        "country": "Austria",
        "confirmed": 15621,
        "death": 600,
        "recovered": 0
    },
    {
        "country": "Croatia",
        "confirmed": 2187,
        "death": 90,
        "recovered": 0
    },
    {
        "country": "Israel",
        "confirmed": 16237,
        "death": 234,
        "recovered": 0
    },
    {
        "country": "Netherlands",
        "confirmed": 40770,
        "death": 5082,
        "recovered": 0
    },
    {
        "country": "Azerbaijan",
        "confirmed": 2519,
        "death": 158,
        "recovered": 0
    },
    {
        "country": "Denmark",
        "confirmed": 9983,
        "death": 506,
        "recovered": 0
    },
    {
        "country": "Georgia",
        "confirmed": 695,
        "death": 12,
        "recovered": 0
    },
    {
        "country": "Greece",
        "confirmed": 2716,
        "death": 151,
        "recovered": 0
    },
    {
        "country": "Romania",
        "confirmed": 13512,
        "death": 803,
        "recovered": 0
    },
    {
        "country": "Finland",
        "confirmed": 5962,
        "death": 267,
        "recovered": 0
    },
    {
        "country": "Russia",
        "confirmed": 155370,
        "death": 11231,
        "recovered": 0
    },
    {
        "country": "Belarus",
        "confirmed": 17489,
        "death": 1872,
        "recovered": 0
    },
    {
        "country": "Belgium",
        "confirmed": 50267,
        "death": 7924,
        "recovered": 0
    },
    {
        "country": "Estonia",
        "confirmed": 1739,
        "death": 60,
        "recovered": 0
    },
    {
        "country": "Ireland",
        "confirmed": 21722,
        "death": 1319,
        "recovered": 0
    },
    {
        "country": "Lithuania",
        "confirmed": 1479,
        "death": 50,
        "recovered": 0
    },
    {
        "country": "Monaco",
        "confirmed": 98,
        "death": 1,
        "recovered": 0
    },
    {
        "country": "North Macedonia",
        "confirmed": 1642,
        "death": 91,
        "recovered": 0
    },
    {
        "country": "San Marino",
        "confirmed": 652,
        "death": 41,
        "recovered": 0
    },
    {
        "country": "Thailand",
        "confirmed": 3009,
        "death": 56,
        "recovered": 0
    },
    {
        "country": "India",
        "confirmed": 46433,
        "death": 4213,
        "recovered": 0
    },
    {
        "country": "Nepal",
        "confirmed": 291,
        "death": 1,
        "recovered": 0
    },
    {
        "country": "Sri Lanka",
        "confirmed": 960,
        "death": 9,
        "recovered": 0
    },
    {
        "country": "Iran",
        "confirmed": 98647,
        "death": 6277,
        "recovered": 0
    },
    {
        "country": "Kuwait",
        "confirmed": 8688,
        "death": 991,
        "recovered": 0
    },
    {
        "country": "Bahrain",
        "confirmed": 4941,
        "death": 385,
        "recovered": 0
    },
    {
        "country": "UAE",
        "confirmed": 14730,
        "death": 796,
        "recovered": 0
    },
    {
        "country": "Iraq",
        "confirmed": 2767,
        "death": 119,
        "recovered": 0
    },
    {
        "country": "Oman",
        "confirmed": 3574,
        "death": 404,
        "recovered": 0
    },
    {
        "country": "Pakistan",
        "confirmed": 21501,
        "death": 1991,
        "recovered": 0
    },
    {
        "country": "Lebanon",
        "confirmed": 902,
        "death": 26,
        "recovered": 0
    },
    {
        "country": "Afghanistan",
        "confirmed": 4664,
        "death": 714,
        "recovered": 0
    },
    {
        "country": "Egypt",
        "confirmed": 9400,
        "death": 525,
        "recovered": 0
    },
    {
        "country": "Qatar",
        "confirmed": 16191,
        "death": 1311,
        "recovered": 0
    },
    {
        "country": "USA",
        "confirmed": 1154985,
        "death": 62406,
        "recovered": 0
    },
    {
        "country": "Canada",
        "confirmed": 59844,
        "death": 3766,
        "recovered": 0
    },
    {
        "country": "Brazil",
        "confirmed": 101147,
        "death": 9888,
        "recovered": 0
    },
    {
        "country": "Mexico",
        "confirmed": 23471,
        "death": 2154,
        "recovered": 0
    },
    {
        "country": "Ecuador",
        "confirmed": 31881,
        "death": 2461,
        "recovered": 0
    },
    {
        "country": "Algeria",
        "confirmed": 5723,
        "death": 502,
        "recovered": 0
    },
    {
        "country": "Nigeria",
        "confirmed": 4399,
        "death": 288,
        "recovered": 0
    },
    {
        "country": "Czechia",
        "confirmed": 8123,
        "death": 280,
        "recovered": 0
    },
    {
        "country": "Iceland",
        "confirmed": 1801,
        "death": 10,
        "recovered": 0
    },
    {
        "country": "Armenia",
        "confirmed": 3392,
        "death": 239,
        "recovered": 0
    },
    {
        "country": "Luxembourg",
        "confirmed": 3886,
        "death": 101,
        "recovered": 0
    },
    {
        "country": "Indonesia",
        "confirmed": 11587,
        "death": 864,
        "recovered": 0
    },
    {
        "country": "Dominican Republic",
        "confirmed": 9882,
        "death": 465,
        "recovered": 0
    },
    {
        "country": "Portugal",
        "confirmed": 25524,
        "death": 1063,
        "recovered": 0
    },
    {
        "country": "Andorra",
        "confirmed": 761,
        "death": 51,
        "recovered": 0
    },
    {
        "country": "Latvia",
        "confirmed": 997,
        "death": 19,
        "recovered": 0
    },
    {
        "country": "Jordan",
        "confirmed": 607,
        "death": 9,
        "recovered": 0
    },
    {
        "country": "Morocco",
        "confirmed": 6063,
        "death": 297,
        "recovered": 0
    },
    {
        "country": "Saudi Arabia",
        "confirmed": 28656,
        "death": 1912,
        "recovered": 0
    },
    {
        "country": "Tunisia",
        "confirmed": 1032,
        "death": 45,
        "recovered": 0
    },
    {
        "country": "Senegal",
        "confirmed": 1709,
        "death": 177,
        "recovered": 0
    },
    {
        "country": "Poland",
        "confirmed": 14006,
        "death": 698,
        "recovered": 0
    },
    {
        "country": "Ukraine",
        "confirmed": 12697,
        "death": 528,
        "recovered": 0
    },
    {
        "country": "Argentina",
        "confirmed": 5924,
        "death": 410,
        "recovered": 0
    },
    {
        "country": "Chile",
        "confirmed": 20643,
        "death": 1647,
        "recovered": 0
    },
    {
        "country": "Bosnia and Herzegovina",
        "confirmed": 2098,
        "death": 103,
        "recovered": 0
    },
    {
        "country": "Hungary",
        "confirmed": 3284,
        "death": 421,
        "recovered": 0
    },
    {
        "country": "Slovenia",
        "confirmed": 1457,
        "death": 102,
        "recovered": 0
    },
    {
        "country": "Liechtenstein",
        "confirmed": 83,
        "death": 1,
        "recovered": 0
    },
    {
        "country": "Gibraltar",
        "confirmed": 147,
        "death": 1,
        "recovered": 0
    },
    {
        "country": "occupied Palestinian territory",
        "confirmed": 555,
        "death": 4,
        "recovered": 0
    },
    {
        "country": "Saint Martin",
        "confirmed": 39,
        "death": 3,
        "recovered": 0
    },
    {
        "country": "St. Barth",
        "confirmed": 6,
        "death": 0,
        "recovered": 0
    },
    {
        "country": "Serbia",
        "confirmed": 9943,
        "death": 209,
        "recovered": 0
    },
    {
        "country": "Bhutan",
        "confirmed": 21,
        "death": 0,
        "recovered": 0
    },
    {
        "country": "Cameroon",
        "confirmed": 2579,
        "death": 154,
        "recovered": 0
    },
    {
        "country": "South Africa",
        "confirmed": 9420,
        "death": 831,
        "recovered": 0
    },
    {
        "country": "Holy See",
        "confirmed": 12,
        "death": 0,
        "recovered": 0
    },
    {
        "country": "Slovakia",
        "confirmed": 1457,
        "death": 26,
        "recovered": 0
    },
    {
        "country": "Colombia",
        "confirmed": 9456,
        "death": 680,
        "recovered": 0
    },
    {
        "country": "Peru",
        "confirmed": 45928,
        "death": 3817,
        "recovered": 0
    },
    {
        "country": "Togo",
        "confirmed": 298,
        "death": 11,
        "recovered": 0
    },
    {
        "country": "Malta",
        "confirmed": 546,
        "death": 6,
        "recovered": 0
    },
    {
        "country": "Bulgaria",
        "confirmed": 1965,
        "death": 91,
        "recovered": 0
    },
    {
        "country": "Moldova",
        "confirmed": 4927,
        "death": 252,
        "recovered": 0
    },
    {
        "country": "Faroe Islands",
        "confirmed": 187,
        "death": 0,
        "recovered": 0
    },
    {
        "country": "Maldives",
        "confirmed": 982,
        "death": 49,
        "recovered": 0
    },
    {
        "country": "Costa Rica",
        "confirmed": 843,
        "death": 8,
        "recovered": 0
    },
    {
        "country": "French Guiana",
        "confirmed": 189,
        "death": 1,
        "recovered": 0
    },
    {
        "country": "Martinique",
        "confirmed": 192,
        "death": 14,
        "recovered": 0
    },
    {
        "country": "Albania",
        "confirmed": 946,
        "death": 31,
        "recovered": 0
    },
    {
        "country": "Bangladesh",
        "confirmed": 10143,
        "death": 969,
        "recovered": 0
    },
    {
        "country": "Paraguay",
        "confirmed": 778,
        "death": 11,
        "recovered": 0
    },
    {
        "country": "Brunei",
        "confirmed": 141,
        "death": 1,
        "recovered": 0
    },
    {
        "country": "Mongolia",
        "confirmed": 135,
        "death": 0,
        "recovered": 0
    },
    {
        "country": "Cyprus",
        "confirmed": 914,
        "death": 23,
        "recovered": 0
    },
    {
        "country": "Guernsey",
        "confirmed": 252,
        "death": 13,
        "recovered": 0
    },
    {
        "country": "Panama",
        "confirmed": 8282,
        "death": 328,
        "recovered": 0
    },
    {
        "country": "Bolivia",
        "confirmed": 2437,
        "death": 275,
        "recovered": 0
    },
    {
        "country": "Jamaica",
        "confirmed": 511,
        "death": 9,
        "recovered": 0
    },
    {
        "country": "Burkina Faso",
        "confirmed": 782,
        "death": 51,
        "recovered": 0
    },
    {
        "country": "DRC",
        "confirmed": 1024,
        "death": 85,
        "recovered": 0
    },
    {
        "country": "French Polynesia",
        "confirmed": 60,
        "death": 0,
        "recovered": 0
    },
    {
        "country": "Turkey",
        "confirmed": 127659,
        "death": 3461,
        "recovered": 0
    },
    {
        "country": "Honduras",
        "confirmed": 1830,
        "death": 175,
        "recovered": 0
    },
    {
        "country": "Ivory Coast",
        "confirmed": 1700,
        "death": 127,
        "recovered": 0
    },
    {
        "country": "Jersey",
        "confirmed": 297,
        "death": 27,
        "recovered": 0
    },
    {
        "country": "Cuba",
        "confirmed": 1766,
        "death": 77,
        "recovered": 0
    },
    {
        "country": "Guyana",
        "confirmed": 116,
        "death": 10,
        "recovered": 0
    },
    {
        "country": "St. Vincent Grenadines",
        "confirmed": 17,
        "death": 0,
        "recovered": 0
    },
    {
        "country": "Sudan",
        "confirmed": 1365,
        "death": 325,
        "recovered": 0
    },
    {
        "country": "Puerto Rico",
        "confirmed": 2198,
        "death": 115,
        "recovered": 0
    },
    {
        "country": "Venezuela",
        "confirmed": 504,
        "death": 10,
        "recovered": 0
    },
    {
        "country": "Antigua and Barbuda",
        "confirmed": 25,
        "death": 3,
        "recovered": 0
    },
    {
        "country": "Guadeloupe",
        "confirmed": 155,
        "death": 13,
        "recovered": 0
    },
    {
        "country": "Trinidad and Tobago",
        "confirmed": 116,
        "death": 8,
        "recovered": 0
    },
    {
        "country": "Cayman Islands",
        "confirmed": 94,
        "death": 1,
        "recovered": 0
    },
    {
        "country": "Ethiopia",
        "confirmed": 306,
        "death": 5,
        "recovered": 0
    },
    {
        "country": "Gabon",
        "confirmed": 863,
        "death": 141,
        "recovered": 0
    },
    {
        "country": "Ghana",
        "confirmed": 4263,
        "death": 437,
        "recovered": 0
    },
    {
        "country": "Guinea",
        "confirmed": 2146,
        "death": 152,
        "recovered": 0
    },
    {
        "country": "Kenya",
        "confirmed": 830,
        "death": 50,
        "recovered": 0
    },
    {
        "country": "Reunion",
        "confirmed": 443,
        "death": 0,
        "recovered": 0
    },
    {
        "country": "Kazakhstan",
        "confirmed": 5138,
        "death": 307,
        "recovered": 0
    },
    {
        "country": "Curacao",
        "confirmed": 16,
        "death": 1,
        "recovered": 0
    },
    {
        "country": "Namibia",
        "confirmed": 16,
        "death": 0,
        "recovered": 0
    },
    {
        "country": "CAR",
        "confirmed": 301,
        "death": 0,
        "recovered": 0
    },
    {
        "country": "Congo",
        "confirmed": 391,
        "death": 15,
        "recovered": 0
    },
    {
        "country": "Equatorial Guinea",
        "confirmed": 690,
        "death": 7,
        "recovered": 0
    },
    {
        "country": "Eswatini",
        "confirmed": 202,
        "death": 2,
        "recovered": 0
    },
    {
        "country": "Mauritania",
        "confirmed": 40,
        "death": 4,
        "recovered": 0
    },
    {
        "country": "Mayotte",
        "confirmed": 1023,
        "death": 67,
        "recovered": 0
    },
    {
        "country": "Uzbekistan",
        "confirmed": 2411,
        "death": 98,
        "recovered": 0
    },
    {
        "country": "Uruguay",
        "confirmed": 732,
        "death": 19,
        "recovered": 0
    },
    {
        "country": "Guatemala",
        "confirmed": 967,
        "death": 176,
        "recovered": 0
    },
    {
        "country": "Saint Lucia",
        "confirmed": 18,
        "death": 0,
        "recovered": 0
    },
    {
        "country": "Suriname",
        "confirmed": 10,
        "death": 1,
        "recovered": 0
    },
    {
        "country": "Rwanda",
        "confirmed": 289,
        "death": 0,
        "recovered": 0
    },
    {
        "country": "Seychelles",
        "confirmed": 11,
        "death": 0,
        "recovered": 0
    },
    {
        "country": "Guam",
        "confirmed": 149,
        "death": 5,
        "recovered": 0
    },
    {
        "country": "Somalia",
        "confirmed": 1054,
        "death": 81,
        "recovered": 0
    },
    {
        "country": "Bahamas",
        "confirmed": 96,
        "death": 11,
        "recovered": 0
    },
    {
        "country": "Grenadines",
        "confirmed": 17,
        "death": 0,
        "recovered": 0
    },
    {
        "country": "Aruba",
        "confirmed": 101,
        "death": 3,
        "recovered": 0
    },
    {
        "country": "U.S. Virgin Islands",
        "confirmed": 69,
        "death": 6,
        "recovered": 0
    },
    {
        "country": "Benin",
        "confirmed": 339,
        "death": 2,
        "recovered": 0
    },
    {
        "country": "Liberia",
        "confirmed": 223,
        "death": 20,
        "recovered": 0
    },
    {
        "country": "Tanzania",
        "confirmed": 509,
        "death": 21,
        "recovered": 0
    },
    {
        "country": "Montenegro",
        "confirmed": 325,
        "death": 9,
        "recovered": 0
    },
    {
        "country": "Kyrgyzstan",
        "confirmed": 1016,
        "death": 38,
        "recovered": 0
    },
    {
        "country": "Greenland",
        "confirmed": 11,
        "death": 0,
        "recovered": 0
    },
    {
        "country": "Djibouti",
        "confirmed": 1210,
        "death": 29,
        "recovered": 0
    },
    {
        "country": "Barbados",
        "confirmed": 85,
        "death": 7,
        "recovered": 0
    },
    {
        "country": "Montserrat",
        "confirmed": 11,
        "death": 1,
        "recovered": 0
    },
    {
        "country": "Mauritius",
        "confirmed": 334,
        "death": 10,
        "recovered": 0
    },
    {
        "country": "Zambia",
        "confirmed": 679,
        "death": 7,
        "recovered": 0
    },
    {
        "country": "Gambia",
        "confirmed": 23,
        "death": 1,
        "recovered": 0
    },
    {
        "country": "Fiji",
        "confirmed": 18,
        "death": 0,
        "recovered": 0
    },
    {
        "country": "New Caledonia",
        "confirmed": 18,
        "death": 0,
        "recovered": 0
    },
    {
        "country": "Herzegovina",
        "confirmed": 1210,
        "death": 44,
        "recovered": 0
    },
    {
        "country": "Bermuda",
        "confirmed": 123,
        "death": 9,
        "recovered": 0
    },
    {
        "country": "El Salvador",
        "confirmed": 998,
        "death": 98,
        "recovered": 0
    },
    {
        "country": "Nicaragua",
        "confirmed": 25,
        "death": 8,
        "recovered": 0
    },
    {
        "country": "Sint Maarten",
        "confirmed": 78,
        "death": 15,
        "recovered": 0
    },
    {
        "country": "Chad",
        "confirmed": 474,
        "death": 50,
        "recovered": 0
    },
    {
        "country": "Niger",
        "confirmed": 889,
        "death": 51,
        "recovered": 0
    },
    {
        "country": "Papua New Guinea",
        "confirmed": 8,
        "death": 0,
        "recovered": 0
    },
    {
        "country": "Isle of Man",
        "confirmed": 334,
        "death": 24,
        "recovered": 0
    },
    {
        "country": "Timor-Leste",
        "confirmed": 24,
        "death": 0,
        "recovered": 0
    },
    {
        "country": "Haiti",
        "confirmed": 310,
        "death": 20,
        "recovered": 0
    },
    {
        "country": "Cabo Verde",
        "confirmed": 328,
        "death": 3,
        "recovered": 0
    },
    {
        "country": "Zimbabwe",
        "confirmed": 44,
        "death": 4,
        "recovered": 0
    },
    {
        "country": "Madagascar",
        "confirmed": 283,
        "death": 0,
        "recovered": 0
    },
    {
        "country": "Angola",
        "confirmed": 48,
        "death": 2,
        "recovered": 0
    },
    {
        "country": "Eritrea",
        "confirmed": 39,
        "death": 0,
        "recovered": 0
    },
    {
        "country": "Uganda",
        "confirmed": 227,
        "death": 0,
        "recovered": 0
    },
    {
        "country": "Kosovo",
        "confirmed": 944,
        "death": 29,
        "recovered": 0
    },
    {
        "country": "Syria",
        "confirmed": 51,
        "death": 3,
        "recovered": 0
    },
    {
        "country": "Grenada",
        "confirmed": 22,
        "death": 0,
        "recovered": 0
    },
    {
        "country": "Mozambique",
        "confirmed": 129,
        "death": 0,
        "recovered": 0
    },
    {
        "country": "Myanmar",
        "confirmed": 182,
        "death": 6,
        "recovered": 0
    },
    {
        "country": "Belize",
        "confirmed": 18,
        "death": 2,
        "recovered": 0
    },
    {
        "country": "Dominica",
        "confirmed": 16,
        "death": 0,
        "recovered": 0
    },
    {
        "country": "Turks and Caicos",
        "confirmed": 12,
        "death": 1,
        "recovered": 0
    },
    {
        "country": "Laos",
        "confirmed": 19,
        "death": 0,
        "recovered": 0
    },
    {
        "country": "Libya",
        "confirmed": 65,
        "death": 3,
        "recovered": 0
    },
    {
        "country": "Saint Kitts and Nevis",
        "confirmed": 15,
        "death": 0,
        "recovered": 0
    },
    {
        "country": "Guinea-Bissau",
        "confirmed": 913,
        "death": 3,
        "recovered": 0
    },
    {
        "country": "Mali",
        "confirmed": 835,
        "death": 48,
        "recovered": 0
    },
    {
        "country": "Anguilla",
        "confirmed": 3,
        "death": 0,
        "recovered": 0
    },
    {
        "country": "British Virgin Islands",
        "confirmed": 8,
        "death": 1,
        "recovered": 0
    },
    {
        "country": "Northern Mariana Islands (Commonwealth of the)",
        "confirmed": 21,
        "death": 2,
        "recovered": 0
    },
    {
        "country": "Botswana",
        "confirmed": 25,
        "death": 1,
        "recovered": 0
    },
    {
        "country": "Burundi",
        "confirmed": 27,
        "death": 1,
        "recovered": 0
    },
    {
        "country": "Sierra Leone",
        "confirmed": 462,
        "death": 29,
        "recovered": 0
    },
    {
        "country": "Malawi",
        "confirmed": 65,
        "death": 3,
        "recovered": 0
    },
    {
        "country": "Bonaire, Sint Eustatius and Saba",
        "confirmed": 6,
        "death": 0,
        "recovered": 0
    },
    {
        "country": "Falkland Islands",
        "confirmed": 13,
        "death": 0,
        "recovered": 0
    },
    {
        "country": "South Sudan",
        "confirmed": 231,
        "death": 1,
        "recovered": 0
    },
    {
        "country": "Sao Tome and Principe",
        "confirmed": 208,
        "death": 7,
        "recovered": 0
    },
    {
        "country": "Saint Pierre Miquelon",
        "confirmed": 1,
        "death": 0,
        "recovered": 0
    },
    {
        "country": "Yemen",
        "confirmed": 126,
        "death": 19,
        "recovered": 0
    },
    {
        "country": "Comoros",
        "confirmed": 11,
        "death": 1,
        "recovered": 0
    },
    {
        "country": "Tajikistan",
        "confirmed": 729,
        "death": 356,
        "recovered": 0
    },
    {
        "country": "Lesotho",
        "confirmed": 1,
        "death": 0,
        "recovered": 0
    }
]